py2jdatetime/__init__.py
py2jdatetime/constants.py
py2jdatetime/patternconverter.py
py2jdatetime-0.0.3.dist-info/METADATA
py2jdatetime-0.0.3.dist-info/WHEEL
py2jdatetime-0.0.3.dist-info/top_level.txt
py2jdatetime-0.0.3.dist-info/RECORD
