Metadata-Version: 2.1
Name: py2jdatetime
Version: 0.0.3
Summary: A package for converting python datetime patterns to java patterns
Home-page: https://github.com/Iddoyadlin/Py2JDatetime
Author: Iddo Yadlin
Author-email: iddoyadlin@gmail.com
License: UNKNOWN
Platform: UNKNOWN
Classifier: Programming Language :: Python :: 3
Classifier: License :: OSI Approved :: MIT License
Classifier: Operating System :: OS Independent
